Processor/final.v
`include "decoder.v"
`include "alu.v"

module mux_2to1(
  input sel,
  input [31:0]in0,
  input [31:0]in1,
  output reg [31:0]out
);

  always @(*) begin
    if (sel == 1'b0) begin
      out = in0;
    end else begin
      out = in1;
    end
  end
  
endmodule

module mux2_2to1(
  input sel,
  input [4:0]in0,
  input [4:0]in1,
  output reg [4:0]out
);

  always @(*) begin
    if (sel == 1'b0) begin
      out = in0;
    end else begin
      out = in1;
    end
  end
  
endmodule

module veda_m(
    input clk,
    input mode,
    input [7:0] address_a,
    input [7:0] address_b,
    input write_enable,
    input [31:0] data_in,
    output reg [31:0] data_out
);
    reg [31:0] mem [31:0];
    // Machine Code for Bubble Sort 
    initial begin
        mem[0] = 32'b00100000000000110000000000000001; //addi r3,r0,1
        mem[1] = 32'b00100000000000010000000000000000; //addi r3,r0,1 
        mem[2] = 32'b00010000100000000000000000001110; //beq r4,r0,end(17)
        mem[3] = 32'b00000000010011110001000000100010; //sub r2,r2,r15
        mem[4] = 32'b00100000000001000000000000000000; //addi r4,r0,0
        mem[5] = 32'b00011100010000110000000000000001; //bgt r2,r3,continue(7)
        mem[6] = 32'b11111100000000000000000000000000; //j outerloop(0)
        mem[7] = 32'b10001100001001010000000000000000; //lw r5,0(r1)
        mem[8] = 32'b10001100001001100000000000000001; //lw r6,1(r1)
        mem[9] = 32'b00011000101001100000000000000100; //ble r5,r6,skipswap(14)
        mem[11] = 32'b10101100001001010000000000000001; //sw r5, 1(r1)
        mem[10]= 32'b10101100001001100000000000000000; //sw r6, 0(r1)
        mem[12]= 32'b00100000000010110000000000000001;
        mem[13]= 32'b00100000000001000000000000000001; //addi r4,r0,1
        mem[14]= 32'b00100000001000010000000000000001; //addi r1,r1,1
        mem[15]= 32'b00100000011000110000000000000001; //addi r3,r3,1
        mem[16]= 32'b11111100000000000000000000000101; //j innerloop(4)
        // mem[15]= 32'b00000000000000000000000000000000; //end
        mem[17] = 32'b10001100000001110000000000000000; //lw r7,0(r0)
        mem[18] = 32'b10001100000010000000000000000001; //lw r8,1(r0)
        mem[19] = 32'b10001100000010010000000000000010; //lw r9,2(r0)
        mem[20] = 32'b10001100000010100000000000000011; //lw r10,3(r0)
        

       


        
        

        

    end
    always @ (*) begin
        // if (mode == 0 &&  write_enable==1) begin
        //     mem[address_a] = data_in;
        //     data_out = data_in;
        // end 
        // else if(mode == 1 &&  write_enable==1) begin
        //     data_out = mem[address_b];
        //     mem[address_b] = data_in;
        // end
        // else if(write_enable==0) begin
        //     data_out = mem[address_b];
        //     //mem[address_b] = data_in;
        // end
        // mem[address_a] = data_in;

        data_out = mem[address_b];

        
    end
endmodule

module veda_m2(
    input clk,
    input mode,
    input [7:0] address_a,
    input [7:0] address_b,
    input write_enable,
    input [31:0] data_in,
    output [31:0] data_out
);
    reg [31:0] mem [31:0];
    initial begin
        
     

        mem[0] = 32'b00000000000000000000000000000010; //2
        mem[1] = 32'b00000000000000000000000000000100; //4
        mem[2] = 32'b00000000000000000000000000000000; //0

  
        

    end
    always @ (posedge clk) begin
        // if (mode == 0 &&  write_enable==1) begin
        //     mem[address_a] = data_in;
        //     data_out = data_in;
        // end 
        // else if(mode == 1 &&  write_enable==1) begin
        //     data_out = mem[address_b];
        //     mem[address_b] = data_in;
        // end
        if(write_enable) begin
            // data_out = mem[address_b];
            mem[address_a] = data_in;
        end
        // mem[address_a] <= data_in;

        //data_out <= mem[address_b];

    end

    assign data_out = (write_enable) ? 0 :mem[address_b];
endmodule

module bubble(input clk, output reg[31:0] c);
    wire mode,write_enable;
    reg [7:0] address_a;
    wire [7:0] address_b,address_b2;
    wire [31:0] data_in,data_out,data_out2;
    wire [31:0] data_in2;
    wire [7:0]  address_a2;
    wire [31:0] a;
    wire [31:0] b;
    // reg [5:0] opcode,func;
    wire [4:0] rs,rt,rd,shamt;

    wire R,I,J; 
    wire branch;
    wire[31:0] out;
    reg [5:0] opcode;
    reg [7:0] jumpadd;

    veda_m Instruc(clk,mode,address_a,address_b,write_enable,data_in,data_out);

    veda_m2 Data(clk,mode,address_a2,address_b2,write_enable,data_in2,data_out2);

    mips_decoder m1(data_out,R,I,J);
    ALU a1(data_out,a,b,R,I,J,out,branch);

    reg [31:0] r [31:0];
    reg [31:0] IR;
    reg [7:0] PC=0;

    reg flag_ins_ex=0;
    initial begin
        r[0] = 32'b00000000000000000000000000000000;
        r[1] = 32'b00000000000000000000000000000000;
        r[2] = 32'b00000000000000000000000000000011;
        r[3] = 32'b00000000000000000000000000000000;
        r[4] = 32'b00000000000000000000000000000001;
        r[5] = 32'b00000000000000000000000000000000;
        r[6] = 32'b00000000000000000000000000000000;
        r[15]= 32'b00000000000000000000000000000001;
    end

    assign a = r[data_out[25:21]];
    assign b1 = r[data_out[20:16]];
    //assign b2 = {{16{1'b0}},data_out[15:0]};
    assign b2 = ((data_out[31:26]==6'b000110) || (data_out[31:26]==6'b000111) || (data_out[31:26]==6'b000100)) ? (b1) : {{16{1'b0}},data_out[15:0]};
    wire [31:0] b1,b2;
    mux_2to1 mux1(R,b2,b1,b);

    //assign r[data_out[15:11]] <= out;
    wire [4:0] d1,d2;

    assign d1 = data_out[15:11];
    assign d2 = data_out[20:16];

    mux2_2to1 mux2(R,d2,d1,rd);

    
    assign address_b = PC;     //instruction fetch

    assign address_b2 =  (data_out[31:26]==6'b001000)? 0 : r[data_out[25:21]] + data_out[15:0];

    assign address_a2 = (data_out[31:26]==6'b101011) ? (r[data_out[25:21]] + data_out[15:0]) : 30;

    assign data_in2 = r[rd];
    assign write_enable = (data_out[31:26]==6'b101011) ? 1 : 0;

    always @(posedge clk) begin
        // address_b = PC;
        IR <= data_out;
        //r[rd] = out;
        if((data_out[31:26]!=6'b000110) && (data_out[31:26]!=6'b000111)) r[rd]=out;
        if(data_out[31:26]==6'b001000) r[rd] = out;
       

        case (data_out[31:26])
            6'b100011: begin  //lw r0, 10(r1)
                //address_b2 = r[data_out[25:21]] + data_out[15:0];
                r[rd]= data_out2;

                PC = PC + 1;
            end

            6'b101011: begin  //sw r0, 10(r1)
                //address_a2 = r[data_out[25:21]] + data_out[15:0];
                // data_in2 = r[rd];

                PC = PC + 1;
            end

            6'b111111: PC <= data_out[7:0];  //j 10

            6'b111110: begin
                jumpadd <= r[IR[4:0]]; //j r0
                PC <= jumpadd[7:0];
            end

            6'b111101: begin
                //jal 10
                r[31] <= PC + 1 ;
                PC <= IR[7:0];
            end

            6'b000101: PC <= PC + 1 + data_out[7:0]; //bne
            6'b000100: begin
              if(branch) PC <= PC + 1 + data_out[7:0];  //beq
              else PC <= PC + 1;
            end
            6'b000111: begin
              if(branch) PC <= PC + 1 + data_out[7:0];  //PC <= PC + 1 + IR[7:0];  //bgt
              else PC <= PC + 1;
            end
            //6'b001101: PC <= PC + 1 + IR[7:0];  //bgte
            6'b000110: begin
              if(branch) PC <= PC + 1 + data_out[7:0];  //PC <= PC + 1 + IR[7:0];  //ble
              else PC <= PC + 1;
            end
            //6'b001101: PC <= PC + 1 + IR[7:0];  //bleq
            //default: PC = PC + 1 + IR[7:0]; 
            default: PC <= PC + 1;
        endcase

    end





    






    
endmodule

Processor/alu.v
module ALU (input[31:0] instruction,a,b, input rtype,itype,jtype, output reg [31:0] c, output reg branch);
    reg [5:0] opcode,func;
    reg [4:0] rs,rt,rd,shamt;
    reg [31:0] const;

    always @(*) begin
        func = instruction[5:0];
        opcode = instruction[31:26];
        if(rtype) begin
            // rs = instruction[25:21];
            // rt = instruction[20:16];
            // rd = instruction[15:11];
            case (func)
                6'b100000: c = a + b;  //add
                6'b100010: c = a - b;  //sub
                6'b100001: c = a + b;  //addu
                6'b100011: c = a - b;  //subu
                6'b100100: c = a & b;  //and
                6'b100101: c = a | b;  //or
                6'b000000: begin       // sll
                    shamt = instruction[10:6];
                    c = a << shamt;
                end
                6'b000010: begin       //srl
                    shamt = instruction[10:6];
                    c = a >> shamt;
                end
                6'b101010: c = (a<b) ? 1 : 0;  //slt
                


                default: c = 0;
            endcase

        end

        else if(itype) begin
            const[31:0] = { {16{1'b0}} ,instruction[15:0] };
            
            case (opcode)
                6'b001000: c = a + const;  //addi
                6'b001001: c = a + const;  //addiu
                //6'b001100: c = a & const;  //andi
                //6'b001101: c = a | const;  //ori
                
                6'b101010: c = (a<const) ? 1 : 0; //slti
                default: c = 0;
            endcase


        end

        if(jtype) begin
            
            case (opcode)
                6'b000101: branch = (a!=b)?1:0;  //bne
                6'b000100: branch = (a==b)?1:0;  //beq

                6'b000111: begin
                    if(a >= b) branch = 1;
                    else branch = 0;
                end//branch = (a>b)?1:0;  //bgt

                //6'b001101: branch = (a>=b)?1:0;  //bgte

                6'b000110: branch = (a<b) ? 1:0;  //ble

                //6'b001101: branch = (a<=b)?1:0;  //bleq
                
                6'b111111: branch = 1;  //j 
                6'b111110: branch = 1;  //jr
                6'b111101: branch = 1;  //jal

                //default: branch=0;
            endcase
        end


    end
endmodule

Processor/decoder.v
module mips_decoder (
    input [31:0] instruction,
    output rtype,itype,jtype
);
wire[5:0] opcode;


assign opcode = instruction[31:26];


// assign rtype = (opcode == 6'b000000) ? 1 : 0;


// assign itype = (opcode == 6'b001000) || (opcode == 6'b001001) || (opcode == 6'b001100) || (opcode == 6'b001101) || (opcode == 6'b101010) || (opcode == 6'b001111) || (opcode == 6'b100000) || (opcode == 6'b100011) || (opcode == 6'b101011) ? 1 : 0;


// //assign jtype = (opcode == 6'b000010) || (opcode == 6'b000011) ? 1 : 0;

// assign jtype = ~(rtype || itype);

assign rtype = (opcode == 6'b000000) ? 1 : 0;


assign itype = (opcode == 6'b001000) || (opcode == 6'b001001) || (opcode == 6'b001100) || (opcode == 6'b001101) || (opcode == 6'b101010) || (opcode == 6'b001111) || (opcode == 6'b100000) || (opcode == 6'b100011) || (opcode == 6'b101011) ? 1 : 0;


assign jtype = ~(rtype || itype);

endmodule

Processor/final_tb.v
`include "final.v"

module test;

    reg clk;
    wire [31:0] c;

    bubble b1(clk,c);

    always #10 clk = ~clk;

    initial begin
        clk = 0;
        // #10 $display
        $dumpfile("test.vcd");
        $dumpvars(0,test);
        // #40 $display("c = %b",c);
        // #50 $display("c = %b",c);
        #8000 $finish;
    end
endmodule

Processor/test.vcd
$date
	Sun Apr 16 21:59:10 2023
$end
$version
	Icarus Verilog
$end
$timescale
	1s
$end
$scope module test $end
$var wire 32 ! c [31:0] $end
$var reg 1 " clk $end
$scope module b1 $end
$var wire 32 # a [31:0] $end
$var wire 8 $ address_b [7:0] $end
$var wire 32 % b1 [31:0] $end
$var wire 1 " clk $end
$var wire 32 & data_in [31:0] $end
$var wire 32 ' data_in2 [31:0] $end
$var wire 1 ( mode $end
$var wire 1 ) write_enable $end
$var wire 5 * rd [4:0] $end
$var wire 32 + out [31:0] $end
$var wire 32 , data_out2 [31:0] $end
$var wire 32 - data_out [31:0] $end
$var wire 5 . d2 [4:0] $end
$var wire 5 / d1 [4:0] $end
$var wire 1 0 branch $end
$var wire 32 1 b2 [31:0] $end
$var wire 32 2 b [31:0] $end
$var wire 8 3 address_b2 [7:0] $end
$var wire 8 4 address_a2 [7:0] $end
$var wire 1 5 R $end
$var wire 1 6 J $end
$var wire 1 7 I $end
$var reg 32 8 IR [31:0] $end
$var reg 8 9 PC [7:0] $end
$var reg 8 : address_a [7:0] $end
$var reg 32 ; c [31:0] $end
$var reg 1 < flag_ins_ex $end
$var reg 8 = jumpadd [7:0] $end
$scope module Data $end
$var wire 8 > address_a [7:0] $end
$var wire 8 ? address_b [7:0] $end
$var wire 1 " clk $end
$var wire 32 @ data_in [31:0] $end
$var wire 1 ( mode $end
$var wire 1 ) write_enable $end
$var wire 32 A data_out [31:0] $end
$upscope $end
$scope module Instruc $end
$var wire 8 B address_a [7:0] $end
$var wire 8 C address_b [7:0] $end
$var wire 1 " clk $end
$var wire 32 D data_in [31:0] $end
$var wire 1 ( mode $end
$var wire 1 ) write_enable $end
$var reg 32 E data_out [31:0] $end
$upscope $end
$scope module a1 $end
$var wire 32 F a [31:0] $end
$var wire 32 G instruction [31:0] $end
$var wire 1 5 rtype $end
$var wire 1 6 jtype $end
$var wire 1 7 itype $end
$var wire 32 H b [31:0] $end
$var reg 1 0 branch $end
$var reg 32 I c [31:0] $end
$var reg 32 J const [31:0] $end
$var reg 6 K func [5:0] $end
$var reg 6 L opcode [5:0] $end
$var reg 5 M shamt [4:0] $end
$upscope $end
$scope module m1 $end
$var wire 32 N instruction [31:0] $end
$var wire 1 6 jtype $end
$var wire 1 5 rtype $end
$var wire 6 O opcode [5:0] $end
$var wire 1 7 itype $end
$upscope $end
$scope module mux1 $end
$var wire 32 P in0 [31:0] $end
$var wire 32 Q in1 [31:0] $end
$var wire 1 5 sel $end
$var reg 32 R out [31:0] $end
$upscope $end
$scope module mux2 $end
$var wire 5 S in0 [4:0] $end
$var wire 5 T in1 [4:0] $end
$var wire 1 5 sel $end
$var reg 5 U out [4:0] $end
$upscope $end
$upscope $end
$upscope $end
$enddefinitions $end
$comment Show the parameter values. $end
$dumpall
$end
#0
$dumpvars
b11 U
b0 T
b11 S
b1 R
b0 Q
b1 P
b1000 O
b100000000000110000000000000001 N
bx M
b1000 L
b1 K
b1 J
b1 I
b1 H
b100000000000110000000000000001 G
b0 F
b100000000000110000000000000001 E
bz D
b0 C
bx B
b10 A
b0 @
b0 ?
b11110 >
bx =
0<
bx ;
bx :
b0 9
bx 8
17
06
05
b11110 4
b0 3
b1 2
b1 1
x0
b0 /
b11 .
b100000000000110000000000000001 -
b10 ,
b1 +
b11 *
0)
z(
b0 '
bz &
b0 %
b0 $
b0 #
0"
bx !
$end
#10
b0 2
b0 H
b0 R
b1 *
b1 U
b0 1
b0 P
b0 +
b0 I
b0 J
b0 K
b1 .
b1 S
b100000000000010000000000000000 -
b100000000000010000000000000000 E
b100000000000010000000000000000 G
b100000000000010000000000000000 N
b1 $
b1 C
b1 9
b100000000000110000000000000001 8
b0 %
b0 Q
b0 '
b0 @
1"
#20
0"
#30
00
16
07
bx ,
bx A
b1111 3
b1111 ?
b0 *
b0 U
b1110 J
b100 L
b1110 K
b100 O
b0 .
b0 S
b1 #
b1 F
b10000100000000000000000001110 -
b10000100000000000000000001110 E
b10000100000000000000000001110 G
b10000100000000000000000001110 N
b10 $
b10 C
b10 9
b100000000000010000000000000000 8
1"
#40
0"
#50
06
b10 +
b10 I
15
b100101 3
b100101 ?
b1 2
b1 H
b1 R
b11 '
b11 @
b10 *
b10 U
b1000000100010 1
b1000000100010 P
b0 L
b100010 K
b0 O
b1111 .
b1111 S
b10 /
b10 T
b1 %
b1 Q
b11 #
b11 F
b10011110001000000100010 -
b10011110001000000100010 E
b10011110001000000100010 G
b10011110001000000100010 N
b11 $
b11 C
b11 9
b10000100000000000000000001110 8
1"
#60
0"
#70
b0 J
17
06
b0 2
b0 H
b0 R
b10 ,
b10 A
05
b100 *
b100 U
b0 1
b0 P
b0 M
b1000 L
b0 K
b1000 O
b100 .
b100 S
b0 /
b0 T
b100000000001000000000000000000 -
b100000000001000000000000000000 E
b100000000001000000000000000000 G
b100000000001000000000000000000 N
b100 $
b100 C
b100 9
b10011110001000000100010 8
b0 3
b0 ?
b0 +
b0 I
b0 #
b0 F
b1 '
b1 @
1"
#80
0"
#90
10
16
07
bx ,
bx A
b11 3
b11 ?
b1 2
b1 H
b1 R
b11 *
b11 U
b1 1
b1 P
b1 J
b111 L
b1 K
b111 O
b11 .
b11 S
b10 #
b10 F
b11100010000110000000000000001 -
b11100010000110000000000000001 E
b11100010000110000000000000001 G
b11100010000110000000000000001 N
b101 $
b101 C
b101 9
b100000000001000000000000000000 8
b1 %
b1 Q
b1 '
b1 @
1"
#100
0"
#110
06
b0 J
17
b10 ,
b10 A
b0 3
b0 ?
b0 2
b0 H
b0 R
b0 '
b0 @
b101 *
b101 U
b0 1
b0 P
b100011 L
b0 K
b100011 O
b101 .
b101 S
b0 %
b0 Q
b0 #
b0 F
b10001100001001010000000000000000 -
b10001100001001010000000000000000 E
b10001100001001010000000000000000 G
b10001100001001010000000000000000 N
b111 $
b111 C
b111 9
b11100010000110000000000000001 8
1"
#120
0"
#130
b10001100001001010000000000000000 8
b100 ,
b100 A
b1 3
b1 ?
b1 2
b1 H
b1 R
b110 *
b110 U
b1 1
b1 P
b1 J
b1 K
b110 .
b110 S
b10001100001001100000000000000001 -
b10001100001001100000000000000001 E
b10001100001001100000000000000001 G
b10001100001001100000000000000001 N
b1000 $
b1000 C
b1000 9
b0 %
b0 Q
b0 '
b0 @
1"
#140
0"
#150
b10001100001001100000000000000001 8
16
07
bx ,
bx A
b110 3
b110 ?
b100 2
b100 H
b100 R
b100 1
b100 P
b100 J
b110 L
b100 K
b110 O
b10 #
b10 F
b11000101001100000000000000100 -
b11000101001100000000000000100 E
b11000101001100000000000000100 G
b11000101001100000000000000100 N
b1001 $
b1001 C
b1001 9
b100 %
b100 Q
b100 '
b100 @
1"
#160
0"
#170
06
b1 +
b1 I
b1 J
17
b10 ,
b10 A
b0 3
b0 ?
b1 2
b1 H
b1 R
b0 '
b0 @
b1 *
b1 U
b1 1
b1 P
b1000 L
b1 K
b1000 O
b1 .
b1 S
b0 %
b0 Q
b0 #
b0 F
b100000001000010000000000000001 -
b100000001000010000000000000001 E
b100000001000010000000000000001 G
b100000001000010000000000000001 N
b1110 $
b1110 C
b1110 9
b11000101001100000000000000100 8
1"
#180
0"
#190
b11 *
b11 U
b11 .
b11 S
b100000011000110000000000000001 -
b100000011000110000000000000001 E
b100000011000110000000000000001 G
b100000011000110000000000000001 N
b1111 $
b1111 C
b1111 9
b100000001000010000000000000001 8
b10 +
b10 I
b1 #
b1 F
b1 %
b1 Q
b1 '
b1 @
1"
#200
0"
#210
16
07
bx ,
bx A
b101 3
b101 ?
b101 2
b101 H
b101 R
b0 *
b0 U
b101 1
b101 P
b101 J
b111111 L
b101 K
b111111 O
b0 .
b0 S
b11111100000000000000000000000101 -
b11111100000000000000000000000101 E
b11111100000000000000000000000101 G
b11111100000000000000000000000101 N
b10000 $
b10000 C
b10000 9
b100000011000110000000000000001 8
b0 +
b0 I
b0 #
b0 F
b0 %
b0 Q
b0 '
b0 @
1"
#220
0"
#230
b11 3
b11 ?
b10 2
b10 H
b10 R
b10 '
b10 @
b11 *
b11 U
b10 1
b10 P
10
b111 L
b1 K
b111 O
b11 .
b11 S
b10 %
b10 Q
b10 #
b10 F
b11100010000110000000000000001 -
b11100010000110000000000000001 E
b11100010000110000000000000001 G
b11100010000110000000000000001 N
b101 $
b101 C
b101 9
b11111100000000000000000000000101 8
1"
#240
0"
#250
06
b0 J
17
b0 2
b0 H
b0 R
b100 ,
b100 A
b0 1
b0 P
b1 3
b1 ?
b101 *
b101 U
b100011 L
b0 K
b100011 O
b101 .
b101 S
b1 #
b1 F
b10001100001001010000000000000000 -
b10001100001001010000000000000000 E
b10001100001001010000000000000000 G
b10001100001001010000000000000000 N
b111 $
b111 C
b111 9
b11100010000110000000000000001 8
1"
#260
0"
#270
b10001100001001010000000000000000 8
b0 ,
b0 A
b10 3
b10 ?
b1 2
b1 H
b1 R
b110 *
b110 U
b1 1
b1 P
b1 J
b1 K
b110 .
b110 S
b10001100001001100000000000000001 -
b10001100001001100000000000000001 E
b10001100001001100000000000000001 G
b10001100001001100000000000000001 N
b1000 $
b1000 C
b1000 9
b100 %
b100 Q
b100 '
b100 @
1"
#280
0"
#290
b10001100001001100000000000000001 8
00
16
07
bx ,
bx A
b1000 3
b1000 ?
b0 2
b0 H
b0 R
b0 1
b0 P
b100 J
b110 L
b100 K
b110 O
b100 #
b100 F
b11000101001100000000000000100 -
b11000101001100000000000000100 E
b11000101001100000000000000100 G
b11000101001100000000000000100 N
b1001 $
b1001 C
b1001 9
b0 %
b0 Q
b0 '
b0 @
1"
#300
0"
#310
06
b0 J
17
b0 ,
b0 A
1)
b1 4
b1 >
b1 3
b1 ?
b101011 L
b0 K
b101011 O
b1 #
b1 F
b10101100001001100000000000000000 -
b10101100001001100000000000000000 E
b10101100001001100000000000000000 G
b10101100001001100000000000000000 N
b1010 $
b1010 C
b1010 9
b11000101001100000000000000100 8
1"
#320
0"
#330
b10101100001001100000000000000000 8
b10 4
b10 >
b10 3
b10 ?
b1 2
b1 H
b1 R
b100 '
b100 @
b101 *
b101 U
b1 1
b1 P
b1 J
b1 K
b101 .
b101 S
b100 %
b100 Q
b10101100001001010000000000000001 -
b10101100001001010000000000000001 E
b10101100001001010000000000000001 G
b10101100001001010000000000000001 N
b1011 $
b1011 C
b1011 9
1"
#340
0"
#350
b10101100001001010000000000000001 8
06
17
b10 ,
b10 A
0)
b11110 4
b11110 >
b0 3
b0 ?
b1011 *
b1011 U
b1 +
b1 I
b1000 L
b1000 O
b1011 .
b1011 S
b0 #
b0 F
b100000000010110000000000000001 -
b100000000010110000000000000001 E
b100000000010110000000000000001 G
b100000000010110000000000000001 N
b1100 $
b1100 C
b1100 9
bx %
bx Q
bx '
bx @
1"
#360
0"
#370
b100 *
b100 U
b100 .
b100 S
b100000000001000000000000000001 -
b100000000001000000000000000001 E
b100000000001000000000000000001 G
b100000000001000000000000000001 N
b1101 $
b1101 C
b1101 9
b100000000010110000000000000001 8
b0 %
b0 Q
b0 '
b0 @
1"
#380
0"
#390
b1 *
b1 U
b10 +
b10 I
b1 .
b1 S
b1 #
b1 F
b100000001000010000000000000001 -
b100000001000010000000000000001 E
b100000001000010000000000000001 G
b100000001000010000000000000001 N
b1110 $
b1110 C
b1110 9
b100000000001000000000000000001 8
b1 %
b1 Q
b1 '
b1 @
1"
#400
0"
#410
b11 *
b11 U
b11 .
b11 S
b100000011000110000000000000001 -
b100000011000110000000000000001 E
b100000011000110000000000000001 G
b100000011000110000000000000001 N
b1111 $
b1111 C
b1111 9
b100000001000010000000000000001 8
b11 +
b11 I
b10 #
b10 F
b10 %
b10 Q
b10 '
b10 @
1"
#420
0"
#430
10
16
07
bx ,
bx A
b101 3
b101 ?
b101 2
b101 H
b101 R
b0 *
b0 U
b101 1
b101 P
b101 J
b111111 L
b101 K
b111111 O
b0 .
b0 S
b11111100000000000000000000000101 -
b11111100000000000000000000000101 E
b11111100000000000000000000000101 G
b11111100000000000000000000000101 N
b10000 $
b10000 C
b10000 9
b100000011000110000000000000001 8
b0 +
b0 I
b0 #
b0 F
b0 %
b0 Q
b0 '
b0 @
1"
#440
0"
#450
b11 3
b11 ?
b11 2
b11 H
b11 R
b11 '
b11 @
b11 *
b11 U
b11 1
b11 P
00
b111 L
b1 K
b111 O
b11 .
b11 S
b11 %
b11 Q
b10 #
b10 F
b11100010000110000000000000001 -
b11100010000110000000000000001 E
b11100010000110000000000000001 G
b11100010000110000000000000001 N
b101 $
b101 C
b101 9
b11111100000000000000000000000101 8
1"
#460
0"
#470
b10 ,
b10 A
b0 3
b0 ?
b0 2
b0 H
b0 R
b0 '
b0 @
b0 *
b0 U
b0 1
b0 P
10
b111111 L
b0 K
b111111 O
b0 .
b0 S
b0 %
b0 Q
b0 #
b0 F
b11111100000000000000000000000000 -
b11111100000000000000000000000000 E
b11111100000000000000000000000000 G
b11111100000000000000000000000000 N
b110 $
b110 C
b110 9
b11100010000110000000000000001 8
1"
#480
0"
#490
06
b1 +
b1 I
b1 J
17
b1 2
b1 H
b1 R
b11 '
b11 @
b11 *
b11 U
b1 1
b1 P
b1000 L
b1 K
b1000 O
b11 .
b11 S
b11 %
b11 Q
b100000000000110000000000000001 -
b100000000000110000000000000001 E
b100000000000110000000000000001 G
b100000000000110000000000000001 N
b0 $
b0 C
b0 9
b11111100000000000000000000000000 8
1"
#500
0"
#510
b0 2
b0 H
b0 R
b1 *
b1 U
b0 1
b0 P
b0 +
b0 I
b0 J
b0 K
b1 .
b1 S
b100000000000010000000000000000 -
b100000000000010000000000000000 E
b100000000000010000000000000000 G
b100000000000010000000000000000 N
b1 $
b1 C
b1 9
b100000000000110000000000000001 8
b10 %
b10 Q
b10 '
b10 @
1"
#520
0"
#530
00
16
07
bx ,
bx A
b1111 3
b1111 ?
b0 *
b0 U
b1110 J
b100 L
b1110 K
b100 O
b0 .
b0 S
b1 #
b1 F
b10000100000000000000000001110 -
b10000100000000000000000001110 E
b10000100000000000000000001110 G
b10000100000000000000000001110 N
b10 $
b10 C
b10 9
b100000000000010000000000000000 8
b0 %
b0 Q
b0 '
b0 @
1"
#540
0"
#550
06
b1 +
b1 I
15
b100100 3
b100100 ?
b1 2
b1 H
b1 R
b10 '
b10 @
b10 *
b10 U
b1000000100010 1
b1000000100010 P
b0 L
b100010 K
b0 O
b1111 .
b1111 S
b10 /
b10 T
b1 %
b1 Q
b10 #
b10 F
b10011110001000000100010 -
b10011110001000000100010 E
b10011110001000000100010 G
b10011110001000000100010 N
b11 $
b11 C
b11 9
b10000100000000000000000001110 8
1"
#560
0"
#570
b0 J
17
06
b0 2
b0 H
b0 R
b10 ,
b10 A
05
b100 *
b100 U
b0 1
b0 P
b1000 L
b0 K
b1000 O
b100 .
b100 S
b0 /
b0 T
b100000000001000000000000000000 -
b100000000001000000000000000000 E
b100000000001000000000000000000 G
b100000000001000000000000000000 N
b100 $
b100 C
b100 9
b10011110001000000100010 8
b0 3
b0 ?
b0 +
b0 I
b0 #
b0 F
b1 '
b1 @
1"
#580
0"
#590
10
16
07
b100 ,
b100 A
b10 3
b10 ?
b1 2
b1 H
b1 R
b11 *
b11 U
b1 1
b1 P
b1 J
b111 L
b1 K
b111 O
b11 .
b11 S
b1 #
b1 F
b11100010000110000000000000001 -
b11100010000110000000000000001 E
b11100010000110000000000000001 G
b11100010000110000000000000001 N
b101 $
b101 C
b101 9
b100000000001000000000000000000 8
b1 %
b1 Q
b1 '
b1 @
1"
#600
0"
#610
06
b0 J
17
b10 ,
b10 A
b0 3
b0 ?
b0 2
b0 H
b0 R
b0 '
b0 @
b101 *
b101 U
b0 1
b0 P
b100011 L
b0 K
b100011 O
b101 .
b101 S
b0 %
b0 Q
b0 #
b0 F
b10001100001001010000000000000000 -
b10001100001001010000000000000000 E
b10001100001001010000000000000000 G
b10001100001001010000000000000000 N
b111 $
b111 C
b111 9
b11100010000110000000000000001 8
1"
#620
0"
#630
b10001100001001010000000000000000 8
b0 ,
b0 A
b1 3
b1 ?
b1 2
b1 H
b1 R
b110 *
b110 U
b1 1
b1 P
b1 J
b1 K
b110 .
b110 S
b10001100001001100000000000000001 -
b10001100001001100000000000000001 E
b10001100001001100000000000000001 G
b10001100001001100000000000000001 N
b1000 $
b1000 C
b1000 9
b0 %
b0 Q
b0 '
b0 @
1"
#640
0"
#650
b10001100001001100000000000000001 8
00
16
07
bx ,
bx A
b110 3
b110 ?
b0 2
b0 H
b0 R
b0 1
b0 P
b100 J
b110 L
b100 K
b110 O
b10 #
b10 F
b11000101001100000000000000100 -
b11000101001100000000000000100 E
b11000101001100000000000000100 G
b11000101001100000000000000100 N
b1001 $
b1001 C
b1001 9
1"
#660
0"
#670
06
b0 J
17
b0 ,
b0 A
1)
b0 4
b0 >
b0 3
b0 ?
b101011 L
b0 K
b101011 O
b0 #
b0 F
b10101100001001100000000000000000 -
b10101100001001100000000000000000 E
b10101100001001100000000000000000 G
b10101100001001100000000000000000 N
b1010 $
b1010 C
b1010 9
b11000101001100000000000000100 8
1"
#680
0"
#690
b10101100001001100000000000000000 8
b1 4
b1 >
b1 3
b1 ?
b1 2
b1 H
b1 R
b10 '
b10 @
b101 *
b101 U
b1 1
b1 P
b1 J
b1 K
b101 .
b101 S
b10 %
b10 Q
b10101100001001010000000000000001 -
b10101100001001010000000000000001 E
b10101100001001010000000000000001 G
b10101100001001010000000000000001 N
b1011 $
b1011 C
b1011 9
1"
#700
0"
#710
b10101100001001010000000000000001 8
06
17
0)
b11110 4
b11110 >
b0 3
b0 ?
b1011 *
b1011 U
b1 +
b1 I
b1000 L
b1000 O
b1011 .
b1011 S
b100000000010110000000000000001 -
b100000000010110000000000000001 E
b100000000010110000000000000001 G
b100000000010110000000000000001 N
b1100 $
b1100 C
b1100 9
b1 %
b1 Q
b1 '
b1 @
1"
#720
0"
#730
b0 '
b0 @
b100 *
b100 U
b100 .
b100 S
b0 %
b0 Q
b100000000001000000000000000001 -
b100000000001000000000000000001 E
b100000000001000000000000000001 G
b100000000001000000000000000001 N
b1101 $
b1101 C
b1101 9
b100000000010110000000000000001 8
1"
#740
0"
#750
b1 *
b1 U
b1 .
b1 S
b100000001000010000000000000001 -
b100000001000010000000000000001 E
b100000001000010000000000000001 G
b100000001000010000000000000001 N
b1110 $
b1110 C
b1110 9
b100000000001000000000000000001 8
b0 %
b0 Q
b0 '
b0 @
1"
#760
0"
#770
b11 *
b11 U
b11 .
b11 S
b100000011000110000000000000001 -
b100000011000110000000000000001 E
b100000011000110000000000000001 G
b100000011000110000000000000001 N
b1111 $
b1111 C
b1111 9
b100000001000010000000000000001 8
b10 +
b10 I
b1 #
b1 F
b1 %
b1 Q
b1 '
b1 @
1"
#780
0"
#790
10
16
07
bx ,
bx A
b101 3
b101 ?
b101 2
b101 H
b101 R
b0 *
b0 U
b101 1
b101 P
b101 J
b111111 L
b101 K
b111111 O
b0 .
b0 S
b11111100000000000000000000000101 -
b11111100000000000000000000000101 E
b11111100000000000000000000000101 G
b11111100000000000000000000000101 N
b10000 $
b10000 C
b10000 9
b100000011000110000000000000001 8
b0 +
b0 I
b0 #
b0 F
b0 %
b0 Q
b0 '
b0 @
1"
#800
0"
